opentimelineio/__init__.py
opentimelineio/_opentime.cpython-310-x86_64-linux-gnu.so
opentimelineio/_otio.cpython-310-x86_64-linux-gnu.so
opentimelineio/exceptions.py
opentimelineio/hooks.py
opentimelineio/media_linker.py
opentimelineio/opentime.py
opentimelineio/test_utils.py
opentimelineio/url_utils.py
opentimelineio/versioning.py
opentimelineio/adapters/__init__.py
opentimelineio/adapters/adapter.py
opentimelineio/adapters/builtin_adapters.plugin_manifest.json
opentimelineio/adapters/file_bundle_utils.py
opentimelineio/adapters/otio_json.py
opentimelineio/adapters/otiod.py
opentimelineio/adapters/otioz.py
opentimelineio/algorithms/__init__.py
opentimelineio/algorithms/filter.py
opentimelineio/algorithms/stack_algo.py
opentimelineio/algorithms/timeline_algo.py
opentimelineio/algorithms/track_algo.py
opentimelineio/console/__init__.py
opentimelineio/console/autogen_plugin_documentation.py
opentimelineio/console/autogen_serialized_datamodel.py
opentimelineio/console/autogen_version_map.py
opentimelineio/console/console_utils.py
opentimelineio/console/otiocat.py
opentimelineio/console/otioconvert.py
opentimelineio/console/otiopluginfo.py
opentimelineio/console/otiostat.py
opentimelineio/console/otiotool.py
opentimelineio/core/__init__.py
opentimelineio/core/_core_utils.py
opentimelineio/core/color.py
opentimelineio/core/composable.py
opentimelineio/core/composition.py
opentimelineio/core/item.py
opentimelineio/core/mediaReference.py
opentimelineio/plugins/__init__.py
opentimelineio/plugins/manifest.py
opentimelineio/plugins/python_plugin.py
opentimelineio/schema/__init__.py
opentimelineio/schema/box2d.py
opentimelineio/schema/clip.py
opentimelineio/schema/effect.py
opentimelineio/schema/external_reference.py
opentimelineio/schema/generator_reference.py
opentimelineio/schema/image_sequence_reference.py
opentimelineio/schema/marker.py
opentimelineio/schema/schemadef.py
opentimelineio/schema/serializable_collection.py
opentimelineio-0.18.1.dist-info/METADATA
opentimelineio-0.18.1.dist-info/WHEEL
opentimelineio-0.18.1.dist-info/entry_points.txt
opentimelineio-0.18.1.dist-info/top_level.txt
opentimelineio-0.18.1.dist-info/RECORD
opentimelineio-0.18.1.dist-info/licenses/LICENSE.txt
opentimelineio-0.18.1.dist-info/licenses/NOTICE.txt
